PyUtilToolKits/__init__.py
PyUtilToolKits/ffff.py
PyUtilToolKits/util_assert.py
PyUtilToolKits/util_log.py
PyUtilToolKits/util_requirements.py
pyutiltoolkits-1.2.4.dist-info/METADATA
pyutiltoolkits-1.2.4.dist-info/WHEEL
pyutiltoolkits-1.2.4.dist-info/top_level.txt
pyutiltoolkits-1.2.4.dist-info/RECORD
