Metadata-Version: 2.4
Name: PyUtilToolKits
Version: 1.2.4
Summary: Python Utils
Author: MysteriousMan
Author-email: MysteriousMan@facebook.com
License: MIT
Keywords: kit
Classifier: Programming Language :: Python :: 3
Classifier: License :: OSI Approved :: MIT License
Classifier: Operating System :: OS Independent
Requires-Python: >=3.11
Requires-Dist: colorlog==6.8.2
Requires-Dist: PyHamcrest==2.1.0
Requires-Dist: chardet==3.0.4
Dynamic: author
Dynamic: author-email
Dynamic: classifier
Dynamic: description
Dynamic: description-content-type
Dynamic: keywords
Dynamic: license
Dynamic: requires-dist
Dynamic: requires-python
Dynamic: summary
